pjax/__init__.py
pjax/support.py
pjax/distributions/__init__.py
pjax/distributions/base.py
pjax/distributions/bounded_continuous.py
pjax/distributions/continuous.py
pjax/distributions/multivariate.py
pjax/transforms/__init__.py
pjax/transforms/base.py
pjax/transforms/scalar.py
pjax/transforms/vector.py
tests/__init__.py
tests/test_demo.py
pjax-0.0.2.dist-info/METADATA
pjax-0.0.2.dist-info/WHEEL
pjax-0.0.2.dist-info/top_level.txt
pjax-0.0.2.dist-info/RECORD
