Metadata-Version: 2.1
Name: pjax
Version: 0.0.2
Summary: Probability distributions for JAX
Home-page: https://github.com/lawortsmann/pjax
Author: lawortsmann
